bk_clustering/__init__.py
bk_clustering/_hierarchy.pyx
bk_clustering/main.py
bk_clustering/run_batch.py
bk_clustering/utilities/__init__.py
bk_clustering/utilities/calculation_utilities.py
bk_clustering/utilities/cluster_calculations.py
bk_clustering/utilities/density_peak.py
bk_clustering/utilities/load_save.py
bk_clustering/utilities/method_comparison.py
bk_clustering/utilities/metrics.py
bk_clustering/utilities/plot_utilities.py
bk_clustering/utilities/postprocessing.py
bk_clustering/utilities/preprocessing.py
bk_clustering/utilities/tree_traversal.py
bk_clustering-0.3.2.dist-info/METADATA
bk_clustering-0.3.2.dist-info/WHEEL
bk_clustering-0.3.2.dist-info/RECORD
