Metadata-Version: 2.1
Name: bk-clustering
Version: 0.3.2
Summary: The package is the implementation of the Burj Khalifa clustering algorithm
Author: Ivan Reznikov
Author-email: ivanreznikov@gmail.com
Requires-Python: >=3.10,<3.12
Classifier: Programming Language :: Python :: 3
Classifier: Programming Language :: Python :: 3.10
Classifier: Programming Language :: Python :: 3.11
Requires-Dist: anytree (>=2.8.0,<3.0.0)
Requires-Dist: arff (>=0.9,<0.10)
Requires-Dist: numpy (==1.23.5)
Requires-Dist: scikit-learn (>=1.2.2,<2.0.0)
Requires-Dist: scipy (>=1.10.1,<2.0.0)
